replit/ai/__init__.py
replit/ai/modelfarm/__init__.py
replit/ai/modelfarm/chat_model.py
replit/ai/modelfarm/completion_model.py
replit/ai/modelfarm/config.py
replit/ai/modelfarm/embed_model.py
replit/ai/modelfarm/exceptions.py
replit/ai/modelfarm/google/language_models/__init__.py
replit/ai/modelfarm/google/language_models/text_embedding_model.py
replit/ai/modelfarm/google/language_models/text_generation_model.py
replit/ai/modelfarm/google/preview/language_models/__init__.py
replit/ai/modelfarm/google/preview/language_models/chat_model.py
replit/ai/modelfarm/google/structs.py
replit/ai/modelfarm/google/utils.py
replit/ai/modelfarm/identity/__init__.py
replit/ai/modelfarm/identity/exceptions.py
replit/ai/modelfarm/identity/goval/__init__.py
replit/ai/modelfarm/identity/goval/api/__init__.py
replit/ai/modelfarm/identity/goval/api/client_pb2.py
replit/ai/modelfarm/identity/goval/api/features/__init__.py
replit/ai/modelfarm/identity/goval/api/features/features_pb2.py
replit/ai/modelfarm/identity/goval/api/repl/__init__.py
replit/ai/modelfarm/identity/goval/api/repl/repl_pb2.py
replit/ai/modelfarm/identity/goval/api/signing_pb2.py
replit/ai/modelfarm/identity/sign.py
replit/ai/modelfarm/identity/verify.py
replit/ai/modelfarm/model.py
replit/ai/modelfarm/replit_identity_token_manager.py
replit/ai/modelfarm/structs.py
replit/tests/ai/modelfarm/__init__.py
replit/tests/ai/modelfarm/google/language_models/test_text_embedding_model.py
replit/tests/ai/modelfarm/google/language_models/test_text_generation_model.py
replit/tests/ai/modelfarm/google/preview/language_model/test_chat_model.py
replit/tests/ai/modelfarm/test_chat_model.py
replit/tests/ai/modelfarm/test_completion_model.py
replit/tests/ai/modelfarm/test_config.py
replit/tests/ai/modelfarm/test_embed_model.py
replit/tests/ai/modelfarm/test_identity.py
replit/tests/ai/modelfarm/test_loadmodel.py
replit_ai-0.0.10.dist-info/LICENSE
replit_ai-0.0.10.dist-info/METADATA
replit_ai-0.0.10.dist-info/WHEEL
replit_ai-0.0.10.dist-info/entry_points.txt
replit_ai-0.0.10.dist-info/RECORD
